Lab 2/testbench/Lab2.v
module Lab2(ADC_CLK_10, SW, LEDR, KEY, HEX0, HEX1, HEX2, HEX3, HEX4, HEX5);
	input  ADC_CLK_10;
	input  [1:0]  KEY;
	input  [9:0]   SW;
	output [9:0] LEDR;
	output [7:0] HEX0;
	output [7:0] HEX1;
	output [7:0] HEX2;
	output [7:0] HEX3;
	output [7:0] HEX4;
	output [7:0] HEX5;
	reg					 clk;
	reg [3:0]		 counter; 
	reg [3:0]  dayOfYearOnes; 
	reg [3:0]  dayOfYearTens; 
	reg [3:0]		   month;
	reg [3:0]		day_tens;
	reg [3:0]		day_ones;
	reg [6:0]	   dayOfYear;
	reg [4:0]		february;
	reg			  clk_enable;
	reg		   fiveHZ_enable;
	assign LEDR[9] =	  SW[9];
	assign LEDR[1] =		clk;
	assign LEDR[0] = clk_enable;
	initial begin
		clk = 0;
		counter = 0; 
		month = 1;
		day_tens = 0;
		day_ones = 1;
		dayOfYear = 1;
		february = 28;
		clk_enable = 0;
		fiveHZ_enable = 0;
	end

	deciSevSeg dayOfYeartens (.tens_enable(1'b1), .inputReg(dayOfYearTens),.outputReg(HEX5));
	deciSevSeg dayOfYearones (.tens_enable(1'b0), .inputReg(dayOfYearOnes),.outputReg(HEX4));
	assign HEX3 = 8'b1111_1111;
	deciSevSeg monthones	 (.tens_enable(1'b0), .inputReg(month),		   .outputReg(HEX2));
	deciSevSeg daytens		 (.tens_enable(1'b1), .inputReg(day_tens),	   .outputReg(HEX1));
	deciSevSeg dayones		 (.tens_enable(1'b0), .inputReg(day_ones),	   .outputReg(HEX0));

	always @(SW[9]) begin
		if(~SW[9]) february <= 28;
		else february <= 29;
	end
	always @(negedge KEY[0]) clk_enable = ~clk_enable;
	always @(negedge KEY[1]) fiveHZ_enable = ~fiveHZ_enable;
	always @(dayOfYear) begin
		dayOfYearOnes <= dayOfYear % 10;
		dayOfYearTens <= dayOfYear / 10;
		if(dayOfYear <= 31) begin
			month <= 1;
			day_tens <= dayOfYear / 10;
			day_ones <= dayOfYear % 10;
		end
		else if(dayOfYear <= (31 + february)) begin
			month <= 2;
			day_tens <= (dayOfYear - 31) / 10;
			day_ones <= (dayOfYear - 31) % 10;
		end
		else if(dayOfYear <= (31 + 31 + february)) begin 
			month <= 3;
			day_tens <= (dayOfYear - (31 + february)) / 10;
			day_ones <= (dayOfYear - (31 + february)) % 10;
		end
		else begin
			month <= 4;
			day_tens = 4'd15; //blank
			day_ones <= (dayOfYear - (31 + february + 31)) % 10;
		end
	end
	always @(posedge ADC_CLK_10) begin
		if(~clk_enable) begin //resets if KEY0 0 is pressed
			clk <= 0;
			counter <= 0;
			dayOfYear <= 1;
		end
		else if(clk_enable) begin
			counter <= counter + 1;
			if(fiveHZ_enable) begin
				if(counter == 1  || counter == 3  || counter == 5  || counter == 7  || counter == 9 ) clk <= 1'b0;
				if(counter == 2  || counter == 4  || counter == 6  || counter == 8  || counter == 10 ) begin
					counter <= 0;
					clk <= 1'b1;
					dayOfYear <= dayOfYear + 1;
				end
			end
			else begin
				if(counter == 5 ) clk <= 1'b0;
				if(counter == 10 ) begin
					counter <= 0;
					clk <= 1'b1;
					dayOfYear <= dayOfYear + 1;
				end
			end
		end
		if(dayOfYear == 100) dayOfYear <= 1;
	end
endmodule

module deciSevSeg(tens_enable, inputReg, outputReg);
	input  [3:0]  inputReg;
	input	   tens_enable;
	output [7:0] outputReg;
	reg    [7:0] outputHEX;
	assign outputReg = outputHEX;
	always @(inputReg) begin
		casex({tens_enable, inputReg})
			default:  outputHEX = 8'b11111111; // blank
			5'b00000: outputHEX = 8'b11000000; //0
			5'bx0001: outputHEX = 8'b11111001; //1
			5'bx0010: outputHEX = 8'b10100100; //2
			5'bx0011: outputHEX = 8'b10110000; //3
			5'bx0100: outputHEX = 8'b10011001; //4
			5'bx0101: outputHEX = 8'b10010010; //5
			5'bx0110: outputHEX = 8'b10000010; //6
			5'bx0111: outputHEX = 8'b11111000; //7
			5'bx1000: outputHEX = 8'b10000000; //8
			5'bx1001: outputHEX = 8'b10010000; //9
		endcase
	end
endmodule

Lab 2/testbench/tb.v
`timescale 1 us / 100 ns

module tb();
//Declaring Test wires and regs.
	wire		    [7:0]		HEX0;
	wire		    [7:0]		HEX1;
	wire		    [7:0]		HEX2;
	wire		    [7:0]		HEX3;
	wire		    [7:0]		HEX4;
	wire		    [7:0]		HEX5;
	wire		    [9:0]		LEDR;
	reg 						 CLK;
	reg 		    [1:0]		 KEY;
	reg				[9:0]		  SW;
	Lab2 U1(
	//Passing vectors to file.   
	.ADC_CLK_10(CLK),
	.SW(SW),
	.LEDR(LEDR),
	.KEY(KEY),
	.HEX0(HEX0),
	.HEX1(HEX1),
	.HEX2(HEX2),
	.HEX3(HEX3),
	.HEX4(HEX4),
	.HEX5(HEX5));

	initial
	begin
		$dumpfile("output.vcd");
		$dumpvars;
		$display("Starting simulation");
		#0 CLK = 0;
		#0 KEY[0] = 1;
		#0 KEY[1] = 1;
		#0  SW[9] = 0;
		#10_000 $display("Simulation ended.");
	end
	initial begin
		#10		KEY[0] = 0; //start clk

		#2_500 KEY[0] = 1;
		#10    KEY[0] = 0; //reset clk and regs

		#500	KEY[0] = 1;
		#500	KEY[0] = 0; //restart clk

		#100	KEY[1] = 0; //enable 5 HZ
		#1_000  SW[9]  = 1; //enable leap year
	end
	always #1 CLK = ~CLK;
	initial  #10_000 $finish;
endmodule

Lab 2/testbench/output.vcd
$date
	Mon Nov 04 19:07:49 2019
$end
$version
	Icarus Verilog
$end
$timescale
	100ns
$end
$scope module tb $end
$var wire 8 ! HEX3 [7:0] $end
$var wire 10 " LEDR [9:0] $end
$var wire 8 # HEX5 [7:0] $end
$var wire 8 $ HEX4 [7:0] $end
$var wire 8 % HEX2 [7:0] $end
$var wire 8 & HEX1 [7:0] $end
$var wire 8 ' HEX0 [7:0] $end
$var reg 1 ( CLK $end
$var reg 2 ) KEY [1:0] $end
$var reg 10 * SW [9:0] $end
$scope module U1 $end
$var wire 1 ( ADC_CLK_10 $end
$var wire 8 + HEX3 [7:0] $end
$var wire 2 , KEY [1:0] $end
$var wire 10 - SW [9:0] $end
$var wire 10 . LEDR [9:0] $end
$var wire 8 / HEX5 [7:0] $end
$var wire 8 0 HEX4 [7:0] $end
$var wire 8 1 HEX2 [7:0] $end
$var wire 8 2 HEX1 [7:0] $end
$var wire 8 3 HEX0 [7:0] $end
$var reg 1 4 clk $end
$var reg 1 5 clk_enable $end
$var reg 4 6 counter [3:0] $end
$var reg 7 7 dayOfYear [6:0] $end
$var reg 4 8 dayOfYearOnes [3:0] $end
$var reg 4 9 dayOfYearTens [3:0] $end
$var reg 4 : day_ones [3:0] $end
$var reg 4 ; day_tens [3:0] $end
$var reg 5 < february [4:0] $end
$var reg 1 = fiveHZ_enable $end
$var reg 4 > month [3:0] $end
$scope module dayOfYearones $end
$var wire 4 ? inputReg [3:0] $end
$var wire 8 @ outputReg [7:0] $end
$var wire 1 A tens_enable $end
$var reg 8 B outputHEX [7:0] $end
$upscope $end
$scope module dayOfYeartens $end
$var wire 4 C inputReg [3:0] $end
$var wire 8 D outputReg [7:0] $end
$var wire 1 E tens_enable $end
$var reg 8 F outputHEX [7:0] $end
$upscope $end
$scope module dayones $end
$var wire 4 G inputReg [3:0] $end
$var wire 8 H outputReg [7:0] $end
$var wire 1 I tens_enable $end
$var reg 8 J outputHEX [7:0] $end
$upscope $end
$scope module daytens $end
$var wire 4 K inputReg [3:0] $end
$var wire 8 L outputReg [7:0] $end
$var wire 1 M tens_enable $end
$var reg 8 N outputHEX [7:0] $end
$upscope $end
$scope module monthones $end
$var wire 4 O inputReg [3:0] $end
$var wire 8 P outputReg [7:0] $end
$var wire 1 Q tens_enable $end
$var reg 8 R outputHEX [7:0] $end
$upscope $end
$upscope $end
$upscope $end
$enddefinitions $end
#0
$dumpvars
b11111001 R
0Q
b11111001 P
b1 O
b11111111 N
1M
b11111111 L
b0 K
b11111001 J
0I
b11111001 H
b1 G
b11111111 F
1E
b11111111 D
b0 C
b11111001 B
0A
b11111001 @
b1 ?
b1 >
0=
b11100 <
b0 ;
b1 :
b0 9
b1 8
b1 7
b0 6
05
04
b11111001 3
b11111111 2
b11111001 1
b11111001 0
b11111111 /
b0zzzzzzz00 .
b0xxxxxxxxx -
b11 ,
b11111111 +
b0xxxxxxxxx *
b11 )
0(
b11111001 '
b11111111 &
b11111001 %
b11111001 $
b11111111 #
b0zzzzzzz00 "
b11111111 !
$end
#10
1(
#20
0(
#30
1(
#40
0(
#50
1(
#60
0(
#70
1(
#80
0(
#90
1(
#100
b0zzzzzzz01 "
b0zzzzzzz01 .
15
0(
b10 )
b10 ,
#110
b1 6
1(
#120
0(
#130
b10 6
1(
#140
0(
#150
b11 6
1(
#160
0(
#170
b100 6
1(
#180
0(
#190
b101 6
1(
#200
0(
#210
b110 6
1(
#220
0(
#230
b111 6
1(
#240
0(
#250
b1000 6
1(
#260
0(
#270
b1001 6
1(
#280
0(
#290
b1010 6
1(
#300
0(
#310
b10100100 '
b10100100 3
b10100100 H
b10100100 J
b10100100 $
b10100100 0
b10100100 @
b10100100 B
b10 :
b10 G
b10 8
b10 ?
b10 7
b0zzzzzzz11 "
b0zzzzzzz11 .
14
b0 6
1(
#320
0(
#330
b1 6
1(
#340
0(
#350
b10 6
1(
#360
0(
#370
b11 6
1(
#380
0(
#390
b100 6
1(
#400
0(
#410
b101 6
1(
#420
0(
#430
b0zzzzzzz01 "
b0zzzzzzz01 .
04
b110 6
1(
#440
0(
#450
b111 6
1(
#460
0(
#470
b1000 6
1(
#480
0(
#490
b1001 6
1(
#500
0(
#510
b1010 6
1(
#520
0(
#530
b10110000 '
b10110000 3
b10110000 H
b10110000 J
b10110000 $
b10110000 0
b10110000 @
b10110000 B
b11 :
b11 G
b11 8
b11 ?
b11 7
b0zzzzzzz11 "
b0zzzzzzz11 .
14
b0 6
1(
#540
0(
#550
b1 6
1(
#560
0(
#570
b10 6
1(
#580
0(
#590
b11 6
1(
#600
0(
#610
b100 6
1(
#620
0(
#630
b101 6
1(
#640
0(
#650
b0zzzzzzz01 "
b0zzzzzzz01 .
04
b110 6
1(
#660
0(
#670
b111 6
1(
#680
0(
#690
b1000 6
1(
#700
0(
#710
b1001 6
1(
#720
0(
#730
b1010 6
1(
#740
0(
#750
b10011001 '
b10011001 3
b10011001 H
b10011001 J
b10011001 $
b10011001 0
b10011001 @
b10011001 B
b100 :
b100 G
b100 8
b100 ?
b100 7
b0zzzzzzz11 "
b0zzzzzzz11 .
14
b0 6
1(
#760
0(
#770
b1 6
1(
#780
0(
#790
b10 6
1(
#800
0(
#810
b11 6
1(
#820
0(
#830
b100 6
1(
#840
0(
#850
b101 6
1(
#860
0(
#870
b0zzzzzzz01 "
b0zzzzzzz01 .
04
b110 6
1(
#880
0(
#890
b111 6
1(
#900
0(
#910
b1000 6
1(
#920
0(
#930
b1001 6
1(
#940
0(
#950
b1010 6
1(
#960
0(
#970
b10010010 '
b10010010 3
b10010010 H
b10010010 J
b10010010 $
b10010010 0
b10010010 @
b10010010 B
b101 :
b101 G
b101 8
b101 ?
b101 7
b0zzzzzzz11 "
b0zzzzzzz11 .
14
b0 6
1(
#980
0(
#990
b1 6
1(
#1000
0(
#1010
b10 6
1(
#1020
0(
#1030
b11 6
1(
#1040
0(
#1050
b100 6
1(
#1060
0(
#1070
b101 6
1(
#1080
0(
#1090
b0zzzzzzz01 "
b0zzzzzzz01 .
04
b110 6
1(
#1100
0(
#1110
b111 6
1(
#1120
0(
#1130
b1000 6
1(
#1140
0(
#1150
b1001 6
1(
#1160
0(
#1170
b1010 6
1(
#1180
0(
#1190
b10000010 '
b10000010 3
b10000010 H
b10000010 J
b10000010 $
b10000010 0
b10000010 @
b10000010 B
b110 :
b110 G
b110 8
b110 ?
b110 7
b0zzzzzzz11 "
b0zzzzzzz11 .
14
b0 6
1(
#1200
0(
#1210
b1 6
1(
#1220
0(
#1230
b10 6
1(
#1240
0(
#1250
b11 6
1(
#1260
0(
#1270
b100 6
1(
#1280
0(
#1290
b101 6
1(
#1300
0(
#1310
b0zzzzzzz01 "
b0zzzzzzz01 .
04
b110 6
1(
#1320
0(
#1330
b111 6
1(
#1340
0(
#1350
b1000 6
1(
#1360
0(
#1370
b1001 6
1(
#1380
0(
#1390
b1010 6
1(
#1400
0(
#1410
b11111000 '
b11111000 3
b11111000 H
b11111000 J
b11111000 $
b11111000 0
b11111000 @
b11111000 B
b111 :
b111 G
b111 8
b111 ?
b111 7
b0zzzzzzz11 "
b0zzzzzzz11 .
14
b0 6
1(
#1420
0(
#1430
b1 6
1(
#1440
0(
#1450
b10 6
1(
#1460
0(
#1470
b11 6
1(
#1480
0(
#1490
b100 6
1(
#1500
0(
#1510
b101 6
1(
#1520
0(
#1530
b0zzzzzzz01 "
b0zzzzzzz01 .
04
b110 6
1(
#1540
0(
#1550
b111 6
1(
#1560
0(
#1570
b1000 6
1(
#1580
0(
#1590
b1001 6
1(
#1600
0(
#1610
b1010 6
1(
#1620
0(
#1630
b10000000 '
b10000000 3
b10000000 H
b10000000 J
b10000000 $
b10000000 0
b10000000 @
b10000000 B
b1000 :
b1000 G
b1000 8
b1000 ?
b1000 7
b0zzzzzzz11 "
b0zzzzzzz11 .
14
b0 6
1(
#1640
0(
#1650
b1 6
1(
#1660
0(
#1670
b10 6
1(
#1680
0(
#1690
b11 6
1(
#1700
0(
#1710
b100 6
1(
#1720
0(
#1730
b101 6
1(
#1740
0(
#1750
b0zzzzzzz01 "
b0zzzzzzz01 .
04
b110 6
1(
#1760
0(
#1770
b111 6
1(
#1780
0(
#1790
b1000 6
1(
#1800
0(
#1810
b1001 6
1(
#1820
0(
#1830
b1010 6
1(
#1840
0(
#1850
b10010000 '
b10010000 3
b10010000 H
b10010000 J
b10010000 $
b10010000 0
b10010000 @
b10010000 B
b1001 :
b1001 G
b1001 8
b1001 ?
b1001 7
b0zzzzzzz11 "
b0zzzzzzz11 .
14
b0 6
1(
#1860
0(
#1870
b1 6
1(
#1880
0(
#1890
b10 6
1(
#1900
0(
#1910
b11 6
1(
#1920
0(
#1930
b100 6
1(
#1940
0(
#1950
b101 6
1(
#1960
0(
#1970
b0zzzzzzz01 "
b0zzzzzzz01 .
04
b110 6
1(
#1980
0(
#1990
b111 6
1(
#2000
0(
#2010
b1000 6
1(
#2020
0(
#2030
b1001 6
1(
#2040
0(
#2050
b1010 6
1(
#2060
0(
#2070
b11000000 '
b11000000 3
b11000000 H
b11000000 J
b11111001 &
b11111001 2
b11111001 L
b11111001 N
b11111001 #
b11111001 /
b11111001 D
b11111001 F
b11000000 $
b11000000 0
b11000000 @
b11000000 B
b0 :
b0 G
b1 ;
b1 K
b1 9
b1 C
b0 8
b0 ?
b1010 7
b0zzzzzzz11 "
b0zzzzzzz11 .
14
b0 6
1(
#2080
0(
#2090
b1 6
1(
#2100
0(
#2110
b10 6
1(
#2120
0(
#2130
b11 6
1(
#2140
0(
#2150
b100 6
1(
#2160
0(
#2170
b101 6
1(
#2180
0(
#2190
b0zzzzzzz01 "
b0zzzzzzz01 .
04
b110 6
1(
#2200
0(
#2210
b111 6
1(
#2220
0(
#2230
b1000 6
1(
#2240
0(
#2250
b1001 6
1(
#2260
0(
#2270
b1010 6
1(
#2280
0(
#2290
b11111001 '
b11111001 3
b11111001 H
b11111001 J
b11111001 $
b11111001 0
b11111001 @
b11111001 B
b1 :
b1 G
b1 8
b1 ?
b1011 7
b0zzzzzzz11 "
b0zzzzzzz11 .
14
b0 6
1(
#2300
0(
#2310
b1 6
1(
#2320
0(
#2330
b10 6
1(
#2340
0(
#2350
b11 6
1(
#2360
0(
#2370
b100 6
1(
#2380
0(
#2390
b101 6
1(
#2400
0(
#2410
b0zzzzzzz01 "
b0zzzzzzz01 .
04
b110 6
1(
#2420
0(
#2430
b111 6
1(
#2440
0(
#2450
b1000 6
1(
#2460
0(
#2470
b1001 6
1(
#2480
0(
#2490
b1010 6
1(
#2500
0(
#2510
b10100100 '
b10100100 3
b10100100 H
b10100100 J
b10100100 $
b10100100 0
b10100100 @
b10100100 B
b10 :
b10 G
b10 8
b10 ?
b1100 7
b0zzzzzzz11 "
b0zzzzzzz11 .
14
b0 6
1(
#2520
0(
#2530
b1 6
1(
#2540
0(
#2550
b10 6
1(
#2560
0(
#2570
b11 6
1(
#2580
0(
#2590
b100 6
1(
#2600
0(
#2610
b101 6
1(
#2620
0(
#2630
b0zzzzzzz01 "
b0zzzzzzz01 .
04
b110 6
1(
#2640
0(
#2650
b111 6
1(
#2660
0(
#2670
b1000 6
1(
#2680
0(
#2690
b1001 6
1(
#2700
0(
#2710
b1010 6
1(
#2720
0(
#2730
b10110000 '
b10110000 3
b10110000 H
b10110000 J
b10110000 $
b10110000 0
b10110000 @
b10110000 B
b11 :
b11 G
b11 8
b11 ?
b1101 7
b0zzzzzzz11 "
b0zzzzzzz11 .
14
b0 6
1(
#2740
0(
#2750
b1 6
1(
#2760
0(
#2770
b10 6
1(
#2780
0(
#2790
b11 6
1(
#2800
0(
#2810
b100 6
1(
#2820
0(
#2830
b101 6
1(
#2840
0(
#2850
b0zzzzzzz01 "
b0zzzzzzz01 .
04
b110 6
1(
#2860
0(
#2870
b111 6
1(
#2880
0(
#2890
b1000 6
1(
#2900
0(
#2910
b1001 6
1(
#2920
0(
#2930
b1010 6
1(
#2940
0(
#2950
b10011001 '
b10011001 3
b10011001 H
b10011001 J
b10011001 $
b10011001 0
b10011001 @
b10011001 B
b100 :
b100 G
b100 8
b100 ?
b1110 7
b0zzzzzzz11 "
b0zzzzzzz11 .
14
b0 6
1(
#2960
0(
#2970
b1 6
1(
#2980
0(
#2990
b10 6
1(
#3000
0(
#3010
b11 6
1(
#3020
0(
#3030
b100 6
1(
#3040
0(
#3050
b101 6
1(
#3060
0(
#3070
b0zzzzzzz01 "
b0zzzzzzz01 .
04
b110 6
1(
#3080
0(
#3090
b111 6
1(
#3100
0(
#3110
b1000 6
1(
#3120
0(
#3130
b1001 6
1(
#3140
0(
#3150
b1010 6
1(
#3160
0(
#3170
b10010010 '
b10010010 3
b10010010 H
b10010010 J
b10010010 $
b10010010 0
b10010010 @
b10010010 B
b101 :
b101 G
b101 8
b101 ?
b1111 7
b0zzzzzzz11 "
b0zzzzzzz11 .
14
b0 6
1(
#3180
0(
#3190
b1 6
1(
#3200
0(
#3210
b10 6
1(
#3220
0(
#3230
b11 6
1(
#3240
0(
#3250
b100 6
1(
#3260
0(
#3270
b101 6
1(
#3280
0(
#3290
b0zzzzzzz01 "
b0zzzzzzz01 .
04
b110 6
1(
#3300
0(
#3310
b111 6
1(
#3320
0(
#3330
b1000 6
1(
#3340
0(
#3350
b1001 6
1(
#3360
0(
#3370
b1010 6
1(
#3380
0(
#3390
b10000010 '
b10000010 3
b10000010 H
b10000010 J
b10000010 $
b10000010 0
b10000010 @
b10000010 B
b110 :
b110 G
b110 8
b110 ?
b10000 7
b0zzzzzzz11 "
b0zzzzzzz11 .
14
b0 6
1(
#3400
0(
#3410
b1 6
1(
#3420
0(
#3430
b10 6
1(
#3440
0(
#3450
b11 6
1(
#3460
0(
#3470
b100 6
1(
#3480
0(
#3490
b101 6
1(
#3500
0(
#3510
b0zzzzzzz01 "
b0zzzzzzz01 .
04
b110 6
1(
#3520
0(
#3530
b111 6
1(
#3540
0(
#3550
b1000 6
1(
#3560
0(
#3570
b1001 6
1(
#3580
0(
#3590
b1010 6
1(
#3600
0(
#3610
b11111000 '
b11111000 3
b11111000 H
b11111000 J
b11111000 $
b11111000 0
b11111000 @
b11111000 B
b111 :
b111 G
b111 8
b111 ?
b10001 7
b0zzzzzzz11 "
b0zzzzzzz11 .
14
b0 6
1(
#3620
0(
#3630
b1 6
1(
#3640
0(
#3650
b10 6
1(
#3660
0(
#3670
b11 6
1(
#3680
0(
#3690
b100 6
1(
#3700
0(
#3710
b101 6
1(
#3720
0(
#3730
b0zzzzzzz01 "
b0zzzzzzz01 .
04
b110 6
1(
#3740
0(
#3750
b111 6
1(
#3760
0(
#3770
b1000 6
1(
#3780
0(
#3790
b1001 6
1(
#3800
0(
#3810
b1010 6
1(
#3820
0(
#3830
b10000000 '
b10000000 3
b10000000 H
b10000000 J
b10000000 $
b10000000 0
b10000000 @
b10000000 B
b1000 :
b1000 G
b1000 8
b1000 ?
b10010 7
b0zzzzzzz11 "
b0zzzzzzz11 .
14
b0 6
1(
#3840
0(
#3850
b1 6
1(
#3860
0(
#3870
b10 6
1(
#3880
0(
#3890
b11 6
1(
#3900
0(
#3910
b100 6
1(
#3920
0(
#3930
b101 6
1(
#3940
0(
#3950
b0zzzzzzz01 "
b0zzzzzzz01 .
04
b110 6
1(
#3960
0(
#3970
b111 6
1(
#3980
0(
#3990
b1000 6
1(
#4000
0(
#4010
b1001 6
1(
#4020
0(
#4030
b1010 6
1(
#4040
0(
#4050
b10010000 '
b10010000 3
b10010000 H
b10010000 J
b10010000 $
b10010000 0
b10010000 @
b10010000 B
b1001 :
b1001 G
b1001 8
b1001 ?
b10011 7
b0zzzzzzz11 "
b0zzzzzzz11 .
14
b0 6
1(
#4060
0(
#4070
b1 6
1(
#4080
0(
#4090
b10 6
1(
#4100
0(
#4110
b11 6
1(
#4120
0(
#4130
b100 6
1(
#4140
0(
#4150
b101 6
1(
#4160
0(
#4170
b0zzzzzzz01 "
b0zzzzzzz01 .
04
b110 6
1(
#4180
0(
#4190
b111 6
1(
#4200
0(
#4210
b1000 6
1(
#4220
0(
#4230
b1001 6
1(
#4240
0(
#4250
b1010 6
1(
#4260
0(
#4270
b11000000 '
b11000000 3
b11000000 H
b11000000 J
b10100100 &
b10100100 2
b10100100 L
b10100100 N
b10100100 #
b10100100 /
b10100100 D
b10100100 F
b11000000 $
b11000000 0
b11000000 @
b11000000 B
b0 :
b0 G
b10 ;
b10 K
b10 9
b10 C
b0 8
b0 ?
b10100 7
b0zzzzzzz11 "
b0zzzzzzz11 .
14
b0 6
1(
#4280
0(
#4290
b1 6
1(
#4300
0(
#4310
b10 6
1(
#4320
0(
#4330
b11 6
1(
#4340
0(
#4350
b100 6
1(
#4360
0(
#4370
b101 6
1(
#4380
0(
#4390
b0zzzzzzz01 "
b0zzzzzzz01 .
04
b110 6
1(
#4400
0(
#4410
b111 6
1(
#4420
0(
#4430
b1000 6
1(
#4440
0(
#4450
b1001 6
1(
#4460
0(
#4470
b1010 6
1(
#4480
0(
#4490
b11111001 '
b11111001 3
b11111001 H
b11111001 J
b11111001 $
b11111001 0
b11111001 @
b11111001 B
b1 :
b1 G
b1 8
b1 ?
b10101 7
b0zzzzzzz11 "
b0zzzzzzz11 .
14
b0 6
1(
#4500
0(
#4510
b1 6
1(
#4520
0(
#4530
b10 6
1(
#4540
0(
#4550
b11 6
1(
#4560
0(
#4570
b100 6
1(
#4580
0(
#4590
b101 6
1(
#4600
0(
#4610
b0zzzzzzz01 "
b0zzzzzzz01 .
04
b110 6
1(
#4620
0(
#4630
b111 6
1(
#4640
0(
#4650
b1000 6
1(
#4660
0(
#4670
b1001 6
1(
#4680
0(
#4690
b1010 6
1(
#4700
0(
#4710
b10100100 '
b10100100 3
b10100100 H
b10100100 J
b10100100 $
b10100100 0
b10100100 @
b10100100 B
b10 :
b10 G
b10 8
b10 ?
b10110 7
b0zzzzzzz11 "
b0zzzzzzz11 .
14
b0 6
1(
#4720
0(
#4730
b1 6
1(
#4740
0(
#4750
b10 6
1(
#4760
0(
#4770
b11 6
1(
#4780
0(
#4790
b100 6
1(
#4800
0(
#4810
b101 6
1(
#4820
0(
#4830
b0zzzzzzz01 "
b0zzzzzzz01 .
04
b110 6
1(
#4840
0(
#4850
b111 6
1(
#4860
0(
#4870
b1000 6
1(
#4880
0(
#4890
b1001 6
1(
#4900
0(
#4910
b1010 6
1(
#4920
0(
#4930
b10110000 '
b10110000 3
b10110000 H
b10110000 J
b10110000 $
b10110000 0
b10110000 @
b10110000 B
b11 :
b11 G
b11 8
b11 ?
b10111 7
b0zzzzzzz11 "
b0zzzzzzz11 .
14
b0 6
1(
#4940
0(
#4950
b1 6
1(
#4960
0(
#4970
b10 6
1(
#4980
0(
#4990
b11 6
1(
#5000
0(
#5010
b100 6
1(
#5020
0(
#5030
b101 6
1(
#5040
0(
#5050
b0zzzzzzz01 "
b0zzzzzzz01 .
04
b110 6
1(
#5060
0(
#5070
b111 6
1(
#5080
0(
#5090
b1000 6
1(
#5100
0(
#5110
b1001 6
1(
#5120
0(
#5130
b1010 6
1(
#5140
0(
#5150
b10011001 '
b10011001 3
b10011001 H
b10011001 J
b10011001 $
b10011001 0
b10011001 @
b10011001 B
b100 :
b100 G
b100 8
b100 ?
b11000 7
b0zzzzzzz11 "
b0zzzzzzz11 .
14
b0 6
1(
#5160
0(
#5170
b1 6
1(
#5180
0(
#5190
b10 6
1(
#5200
0(
#5210
b11 6
1(
#5220
0(
#5230
b100 6
1(
#5240
0(
#5250
b101 6
1(
#5260
0(
#5270
b0zzzzzzz01 "
b0zzzzzzz01 .
04
b110 6
1(
#5280
0(
#5290
b111 6
1(
#5300
0(
#5310
b1000 6
1(
#5320
0(
#5330
b1001 6
1(
#5340
0(
#5350
b1010 6
1(
#5360
0(
#5370
b10010010 '
b10010010 3
b10010010 H
b10010010 J
b10010010 $
b10010010 0
b10010010 @
b10010010 B
b101 :
b101 G
b101 8
b101 ?
b11001 7
b0zzzzzzz11 "
b0zzzzzzz11 .
14
b0 6
1(
#5380
0(
#5390
b1 6
1(
#5400
0(
#5410
b10 6
1(
#5420
0(
#5430
b11 6
1(
#5440
0(
#5450
b100 6
1(
#5460
0(
#5470
b101 6
1(
#5480
0(
#5490
b0zzzzzzz01 "
b0zzzzzzz01 .
04
b110 6
1(
#5500
0(
#5510
b111 6
1(
#5520
0(
#5530
b1000 6
1(
#5540
0(
#5550
b1001 6
1(
#5560
0(
#5570
b1010 6
1(
#5580
0(
#5590
b10000010 '
b10000010 3
b10000010 H
b10000010 J
b10000010 $
b10000010 0
b10000010 @
b10000010 B
b110 :
b110 G
b110 8
b110 ?
b11010 7
b0zzzzzzz11 "
b0zzzzzzz11 .
14
b0 6
1(
#5600
0(
#5610
b1 6
1(
#5620
0(
#5630
b10 6
1(
#5640
0(
#5650
b11 6
1(
#5660
0(
#5670
b100 6
1(
#5680
0(
#5690
b101 6
1(
#5700
0(
#5710
b0zzzzzzz01 "
b0zzzzzzz01 .
04
b110 6
1(
#5720
0(
#5730
b111 6
1(
#5740
0(
#5750
b1000 6
1(
#5760
0(
#5770
b1001 6
1(
#5780
0(
#5790
b1010 6
1(
#5800
0(
#5810
b11111000 '
b11111000 3
b11111000 H
b11111000 J
b11111000 $
b11111000 0
b11111000 @
b11111000 B
b111 :
b111 G
b111 8
b111 ?
b11011 7
b0zzzzzzz11 "
b0zzzzzzz11 .
14
b0 6
1(
#5820
0(
#5830
b1 6
1(
#5840
0(
#5850
b10 6
1(
#5860
0(
#5870
b11 6
1(
#5880
0(
#5890
b100 6
1(
#5900
0(
#5910
b101 6
1(
#5920
0(
#5930
b0zzzzzzz01 "
b0zzzzzzz01 .
04
b110 6
1(
#5940
0(
#5950
b111 6
1(
#5960
0(
#5970
b1000 6
1(
#5980
0(
#5990
b1001 6
1(
#6000
0(
#6010
b1010 6
1(
#6020
0(
#6030
b10000000 '
b10000000 3
b10000000 H
b10000000 J
b10000000 $
b10000000 0
b10000000 @
b10000000 B
b1000 :
b1000 G
b1000 8
b1000 ?
b11100 7
b0zzzzzzz11 "
b0zzzzzzz11 .
14
b0 6
1(
#6040
0(
#6050
b1 6
1(
#6060
0(
#6070
b10 6
1(
#6080
0(
#6090
b11 6
1(
#6100
0(
#6110
b100 6
1(
#6120
0(
#6130
b101 6
1(
#6140
0(
#6150
b0zzzzzzz01 "
b0zzzzzzz01 .
04
b110 6
1(
#6160
0(
#6170
b111 6
1(
#6180
0(
#6190
b1000 6
1(
#6200
0(
#6210
b1001 6
1(
#6220
0(
#6230
b1010 6
1(
#6240
0(
#6250
b10010000 '
b10010000 3
b10010000 H
b10010000 J
b10010000 $
b10010000 0
b10010000 @
b10010000 B
b1001 :
b1001 G
b1001 8
b1001 ?
b11101 7
b0zzzzzzz11 "
b0zzzzzzz11 .
14
b0 6
1(
#6260
0(
#6270
b1 6
1(
#6280
0(
#6290
b10 6
1(
#6300
0(
#6310
b11 6
1(
#6320
0(
#6330
b100 6
1(
#6340
0(
#6350
b101 6
1(
#6360
0(
#6370
b0zzzzzzz01 "
b0zzzzzzz01 .
04
b110 6
1(
#6380
0(
#6390
b111 6
1(
#6400
0(
#6410
b1000 6
1(
#6420
0(
#6430
b1001 6
1(
#6440
0(
#6450
b1010 6
1(
#6460
0(
#6470
b11000000 '
b11000000 3
b11000000 H
b11000000 J
b10110000 &
b10110000 2
b10110000 L
b10110000 N
b10110000 #
b10110000 /
b10110000 D
b10110000 F
b11000000 $
b11000000 0
b11000000 @
b11000000 B
b0 :
b0 G
b11 ;
b11 K
b11 9
b11 C
b0 8
b0 ?
b11110 7
b0zzzzzzz11 "
b0zzzzzzz11 .
14
b0 6
1(
#6480
0(
#6490
b1 6
1(
#6500
0(
#6510
b10 6
1(
#6520
0(
#6530
b11 6
1(
#6540
0(
#6550
b100 6
1(
#6560
0(
#6570
b101 6
1(
#6580
0(
#6590
b0zzzzzzz01 "
b0zzzzzzz01 .
04
b110 6
1(
#6600
0(
#6610
b111 6
1(
#6620
0(
#6630
b1000 6
1(
#6640
0(
#6650
b1001 6
1(
#6660
0(
#6670
b1010 6
1(
#6680
0(
